LICENSE.txt
README.md
setup.py
evque/__init__.py
evque/evque.py
evque.egg-info/PKG-INFO
evque.egg-info/SOURCES.txt
evque.egg-info/dependency_links.txt
evque.egg-info/top_level.txt