Metadata-Version: 2.1
Name: evque
Version: 1.4.1
Summary: A simple event queue library with support for topics.
Home-page: UNKNOWN
Author: Ahmad Siavashi
Author-email: siavashi@aut.ac.ir
License: UNKNOWN
Platform: UNKNOWN
Classifier: Development Status :: 5 - Production/Stable
Classifier: Intended Audience :: Developers
Classifier: License :: OSI Approved :: GNU General Public License v3 (GPLv3)
Classifier: Programming Language :: Python :: 3.7
Classifier: Programming Language :: Python :: 3.8
Classifier: Programming Language :: Python :: 3.9
License-File: LICENSE.txt
